{
  "content_scale": 1.0,
  "armature_data": [
    {
      "strVersion": "1.6.0.0",
      "version": 1.6,
      "name": "FinalAnimation_enemy1",
      "bone_data": [
        {
          "name": "FireBall",
          "parent": "",
          "dI": 12,
          "x": 11.153842926025391,
          "y": 52.558982849121094,
          "z": 6,
          "cX": 1.0,
          "cY": 1.0,
          "kX": 0.0,
          "kY": 0.0,
          "arrow_x": 0.0,
          "arrow_y": 0.0,
          "effectbyskeleton": false,
          "bl": 0,
          "display_data": [
            {
              "name": "WizardFireballProjectile_Sprite_0.png",
              "displayType": 0,
              "skin_data": [
                {
                  "x": 0.0,
                  "y": 0.0,
                  "cX": 1.0,
                  "cY": 1.0,
                  "kX": 0.0,
                  "kY": 0.0
                }
              ]
            },
            {
              "name": "WizardFireballProjectileExplosion_Sprite_7.png",
              "displayType": 0,
              "skin_data": [
                {
                  "x": 0.0,
                  "y": 0.0,
                  "cX": 1.0,
                  "cY": 1.0,
                  "kX": 0.0,
                  "kY": 0.0
                }
              ]
            },
            {
              "name": "WizardFireballProjectile_Sprite_1.png",
              "displayType": 0,
              "skin_data": [
                {
                  "x": 0.0,
                  "y": 0.0,
                  "cX": 1.0,
                  "cY": 1.0,
                  "kX": 0.0,
                  "kY": 0.0
                }
              ]
            },
            {
              "name": "WizardFireballProjectile_Sprite_2.png",
              "displayType": 0,
              "skin_data": [
                {
                  "x": 0.0,
                  "y": 0.0,
                  "cX": 1.0,
                  "cY": 1.0,
                  "kX": 0.0,
                  "kY": 0.0
                }
              ]
            },
            {
              "name": "WizardFireballProjectile_Sprite_3.png",
              "displayType": 0,
              "skin_data": [
                {
                  "x": 0.0,
                  "y": 0.0,
                  "cX": 1.0,
                  "cY": 1.0,
                  "kX": 0.0,
                  "kY": 0.0
                }
              ]
            },
            {
              "name": "WizardFireballProjectileExplosion_Sprite_0.png",
              "displayType": 0,
              "skin_data": [
                {
                  "x": 0.0,
                  "y": 0.0,
                  "cX": 1.0,
                  "cY": 1.0,
                  "kX": 0.0,
                  "kY": 0.0
                }
              ]
            },
            {
              "name": "WizardFireballProjectileExplosion_Sprite_1.png",
              "displayType": 0,
              "skin_data": [
                {
                  "x": 0.0,
                  "y": 0.0,
                  "cX": 1.0,
                  "cY": 1.0,
                  "kX": 0.0,
                  "kY": 0.0
                }
              ]
            },
            {
              "name": "WizardFireballProjectileExplosion_Sprite_2.png",
              "displayType": 0,
              "skin_data": [
                {
                  "x": 0.0,
                  "y": 0.0,
                  "cX": 1.0,
                  "cY": 1.0,
                  "kX": 0.0,
                  "kY": 0.0
                }
              ]
            },
            {
              "name": "WizardFireballProjectileExplosion_Sprite_3.png",
              "displayType": 0,
              "skin_data": [
                {
                  "x": 0.0,
                  "y": 0.0,
                  "cX": 1.0,
                  "cY": 1.0,
                  "kX": 0.0,
                  "kY": 0.0
                }
              ]
            },
            {
              "name": "WizardFireballProjectileExplosion_Sprite_4.png",
              "displayType": 0,
              "skin_data": [
                {
                  "x": 0.0,
                  "y": 0.0,
                  "cX": 1.0,
                  "cY": 1.0,
                  "kX": 0.0,
                  "kY": 0.0
                }
              ]
            },
            {
              "name": "WizardFireballProjectileExplosion_Sprite_5.png",
              "displayType": 0,
              "skin_data": [
                {
                  "x": 0.0,
                  "y": 0.0,
                  "cX": 1.0,
                  "cY": 1.0,
                  "kX": 0.0,
                  "kY": 0.0
                }
              ]
            },
            {
              "name": "WizardFireballProjectileExplosion_Sprite_6.png",
              "displayType": 0,
              "skin_data": [
                {
                  "x": 0.0,
                  "y": 0.0,
                  "cX": 1.0,
                  "cY": 1.0,
                  "kX": 0.0,
                  "kY": 0.0
                }
              ]
            },
            {
              "name": "ExplosionBrown_Sprite_0.png",
              "displayType": 0,
              "skin_data": [
                {
                  "x": 0.0,
                  "y": 0.0,
                  "cX": 1.0,
                  "cY": 1.0,
                  "kX": 0.0,
                  "kY": 0.0
                }
              ]
            }
          ]
        },
        {
          "name": "Fire_Copy5",
          "parent": "",
          "dI": -1,
          "x": 14.487180709838867,
          "y": 52.046165466308594,
          "z": 5,
          "cX": 1.0,
          "cY": 1.0,
          "kX": 0.0,
          "kY": 0.0,
          "arrow_x": 0.0,
          "arrow_y": 0.0,
          "effectbyskeleton": false,
          "bl": 0,
          "display_data": [
            {
              "name": "WizardFireParticle_Sprite_0.png",
              "displayType": 0,
              "skin_data": [
                {
                  "x": 0.0,
                  "y": 0.0,
                  "cX": 1.0,
                  "cY": 1.0,
                  "kX": 0.0,
                  "kY": 0.0
                }
              ]
            },
            {
              "name": "WizardFireballProjectileExplosion_Sprite_7.png",
              "displayType": 0,
              "skin_data": [
                {
                  "x": 0.0,
                  "y": 0.0,
                  "cX": 1.0,
                  "cY": 1.0,
                  "kX": 0.0,
                  "kY": 0.0
                }
              ]
            }
          ]
        },
        {
          "name": "Fire_Copy6",
          "parent": "",
          "dI": -1,
          "x": 14.487180709838867,
          "y": 52.046165466308594,
          "z": 4,
          "cX": 1.0,
          "cY": 1.0,
          "kX": 0.0,
          "kY": 0.0,
          "arrow_x": 0.0,
          "arrow_y": 0.0,
          "effectbyskeleton": false,
          "bl": 0,
          "display_data": [
            {
              "name": "WizardFireParticle_Sprite_0.png",
              "displayType": 0,
              "skin_data": [
                {
                  "x": 0.0,
                  "y": 0.0,
                  "cX": 1.0,
                  "cY": 1.0,
                  "kX": 0.0,
                  "kY": 0.0
                }
              ]
            },
            {
              "name": "WizardFireballProjectileExplosion_Sprite_7.png",
              "displayType": 0,
              "skin_data": [
                {
                  "x": 0.0,
                  "y": 0.0,
                  "cX": 1.0,
                  "cY": 1.0,
                  "kX": 0.0,
                  "kY": 0.0
                }
              ]
            }
          ]
        },
        {
          "name": "Fire_Copy7",
          "parent": "",
          "dI": -1,
          "x": 14.487180709838867,
          "y": 52.046165466308594,
          "z": 3,
          "cX": 1.0,
          "cY": 1.0,
          "kX": 0.0,
          "kY": 0.0,
          "arrow_x": 0.0,
          "arrow_y": 0.0,
          "effectbyskeleton": false,
          "bl": 0,
          "display_data": [
            {
              "name": "WizardFireParticle_Sprite_0.png",
              "displayType": 0,
              "skin_data": [
                {
                  "x": 0.0,
                  "y": 0.0,
                  "cX": 1.0,
                  "cY": 1.0,
                  "kX": 0.0,
                  "kY": 0.0
                }
              ]
            },
            {
              "name": "WizardFireballProjectileExplosion_Sprite_7.png",
              "displayType": 0,
              "skin_data": [
                {
                  "x": 0.0,
                  "y": 0.0,
                  "cX": 1.0,
                  "cY": 1.0,
                  "kX": 0.0,
                  "kY": 0.0
                }
              ]
            }
          ]
        },
        {
          "name": "Fire",
          "parent": "",
          "dI": -1,
          "x": 14.487180709838867,
          "y": 52.046165466308594,
          "z": 2,
          "cX": 1.0,
          "cY": 1.0,
          "kX": 0.0,
          "kY": 0.0,
          "arrow_x": 0.0,
          "arrow_y": 0.0,
          "effectbyskeleton": false,
          "bl": 0,
          "display_data": [
            {
              "name": "WizardFireParticle_Sprite_0.png",
              "displayType": 0,
              "skin_data": [
                {
                  "x": 0.0,
                  "y": 0.0,
                  "cX": 1.0,
                  "cY": 1.0,
                  "kX": 0.0,
                  "kY": 0.0
                }
              ]
            },
            {
              "name": "WizardFireballProjectileExplosion_Sprite_7.png",
              "displayType": 0,
              "skin_data": [
                {
                  "x": 0.0,
                  "y": 0.0,
                  "cX": 1.0,
                  "cY": 1.0,
                  "kX": 0.0,
                  "kY": 0.0
                }
              ]
            }
          ]
        },
        {
          "name": "Body",
          "parent": "",
          "dI": -1,
          "x": 0.0,
          "y": 0.0,
          "z": 1,
          "cX": 1.0,
          "cY": 1.0,
          "kX": 0.0,
          "kY": 0.0,
          "arrow_x": 0.0,
          "arrow_y": 0.0,
          "effectbyskeleton": false,
          "bl": 0,
          "display_data": [
            {
              "name": "EnemyWizardIdle_Sprite_0.png",
              "displayType": 0,
              "skin_data": [
                {
                  "x": 0.0,
                  "y": 0.0,
                  "cX": 1.0,
                  "cY": 1.0,
                  "kX": 0.0,
                  "kY": 0.0
                }
              ]
            },
            {
              "name": "EnemyWizardIdle_Sprite_1.png",
              "displayType": 0,
              "skin_data": [
                {
                  "x": 0.0,
                  "y": 0.0,
                  "cX": 1.0,
                  "cY": 1.0,
                  "kX": 0.0,
                  "kY": 0.0
                }
              ]
            },
            {
              "name": "EnemyWizardIdle_Sprite_2.png",
              "displayType": 0,
              "skin_data": [
                {
                  "x": 0.0,
                  "y": 0.0,
                  "cX": 1.0,
                  "cY": 1.0,
                  "kX": 0.0,
                  "kY": 0.0
                }
              ]
            },
            {
              "name": "EnemyWizardIdle_Sprite_3.png",
              "displayType": 0,
              "skin_data": [
                {
                  "x": 0.0,
                  "y": 0.0,
                  "cX": 1.0,
                  "cY": 1.0,
                  "kX": 0.0,
                  "kY": 0.0
                }
              ]
            },
            {
              "name": "EnemyWizardSpell_Sprite_0.png",
              "displayType": 0,
              "skin_data": [
                {
                  "x": 0.0,
                  "y": 0.0,
                  "cX": 1.0,
                  "cY": 1.0,
                  "kX": 0.0,
                  "kY": 0.0
                }
              ]
            },
            {
              "name": "EnemyWizardSpell_Sprite_1.png",
              "displayType": 0,
              "skin_data": [
                {
                  "x": 0.0,
                  "y": 0.0,
                  "cX": 1.0,
                  "cY": 1.0,
                  "kX": 0.0,
                  "kY": 0.0
                }
              ]
            },
            {
              "name": "EnemyWizardSpell_Sprite_2.png",
              "displayType": 0,
              "skin_data": [
                {
                  "x": 0.0,
                  "y": 0.0,
                  "cX": 1.0,
                  "cY": 1.0,
                  "kX": 0.0,
                  "kY": 0.0
                }
              ]
            },
            {
              "name": "EnemyWizardSpell_Sprite_3.png",
              "displayType": 0,
              "skin_data": [
                {
                  "x": 0.0,
                  "y": 0.0,
                  "cX": 1.0,
                  "cY": 1.0,
                  "kX": 0.0,
                  "kY": 0.0
                }
              ]
            },
            {
              "name": "EnemyWizardSpell_Sprite_4.png",
              "displayType": 0,
              "skin_data": [
                {
                  "x": 0.0,
                  "y": 0.0,
                  "cX": 1.0,
                  "cY": 1.0,
                  "kX": 0.0,
                  "kY": 0.0
                }
              ]
            },
            {
              "name": "EnemyWizardSpell_Sprite_5.png",
              "displayType": 0,
              "skin_data": [
                {
                  "x": 0.0,
                  "y": 0.0,
                  "cX": 1.0,
                  "cY": 1.0,
                  "kX": 0.0,
                  "kY": 0.0
                }
              ]
            },
            {
              "name": "EnemyWizardSpell_Sprite_6.png",
              "displayType": 0,
              "skin_data": [
                {
                  "x": 0.0,
                  "y": 0.0,
                  "cX": 1.0,
                  "cY": 1.0,
                  "kX": 0.0,
                  "kY": 0.0
                }
              ]
            },
            {
              "name": "EnemyWizardSpell_Sprite_7.png",
              "displayType": 0,
              "skin_data": [
                {
                  "x": 0.0,
                  "y": 0.0,
                  "cX": 1.0,
                  "cY": 1.0,
                  "kX": 0.0,
                  "kY": 0.0
                }
              ]
            },
            {
              "name": "EnemyWizardSpell_Sprite_8.png",
              "displayType": 0,
              "skin_data": [
                {
                  "x": 0.0,
                  "y": 0.0,
                  "cX": 1.0,
                  "cY": 1.0,
                  "kX": 0.0,
                  "kY": 0.0
                }
              ]
            },
            {
              "name": "EnemyWizardSpell_Sprite_9.png",
              "displayType": 0,
              "skin_data": [
                {
                  "x": 0.0,
                  "y": 0.0,
                  "cX": 1.0,
                  "cY": 1.0,
                  "kX": 0.0,
                  "kY": 0.0
                }
              ]
            },
            {
              "name": "EnemyWizardSpell_Sprite_10.png",
              "displayType": 0,
              "skin_data": [
                {
                  "x": 0.0,
                  "y": 0.0,
                  "cX": 1.0,
                  "cY": 1.0,
                  "kX": 0.0,
                  "kY": 0.0
                }
              ]
            },
            {
              "name": "EnemyWizardSpell_Sprite_11.png",
              "displayType": 0,
              "skin_data": [
                {
                  "x": 0.0,
                  "y": 0.0,
                  "cX": 1.0,
                  "cY": 1.0,
                  "kX": 0.0,
                  "kY": 0.0
                }
              ]
            },
            {
              "name": "EnemyWizardSpell_Sprite_12.png",
              "displayType": 0,
              "skin_data": [
                {
                  "x": 0.0,
                  "y": 0.0,
                  "cX": 1.0,
                  "cY": 1.0,
                  "kX": 0.0,
                  "kY": 0.0
                }
              ]
            }
          ]
        }
      ]
    }
  ],
  "animation_data": [
    {
      "name": "FinalAnimation_enemy1",
      "mov_data": [
        {
          "name": "Idle",
          "dr": 29,
          "lp": true,
          "to": 0,
          "drTW": 0,
          "twE": 0,
          "sc": 1.0,
          "mov_bone_data": [
            {
              "name": "Body",
              "dl": 0.0,
              "frame_data": [
                {
                  "dI": 0,
                  "x": 0.0,
                  "y": 0.0,
                  "z": 0,
                  "cX": 1.0,
                  "cY": 1.0,
                  "kX": 0.0,
                  "kY": 0.0,
                  "fi": 0,
                  "twE": 0,
                  "tweenFrame": true,
                  "bd_src": 1,
                  "bd_dst": 771
                },
                {
                  "dI": 1,
                  "x": 0.0,
                  "y": 0.0,
                  "z": 0,
                  "cX": 1.0,
                  "cY": 1.0,
                  "kX": 0.0,
                  "kY": 0.0,
                  "fi": 7,
                  "twE": 0,
                  "tweenFrame": true,
                  "bd_src": 1,
                  "bd_dst": 771
                },
                {
                  "dI": 2,
                  "x": 0.0,
                  "y": 0.0,
                  "z": 0,
                  "cX": 1.0,
                  "cY": 1.0,
                  "kX": 0.0,
                  "kY": 0.0,
                  "fi": 14,
                  "twE": 0,
                  "tweenFrame": true,
                  "bd_src": 1,
                  "bd_dst": 771
                },
                {
                  "dI": 3,
                  "x": 0.0,
                  "y": 0.0,
                  "z": 0,
                  "cX": 1.0,
                  "cY": 1.0,
                  "kX": 0.0,
                  "kY": 0.0,
                  "fi": 21,
                  "twE": 0,
                  "tweenFrame": true,
                  "bd_src": 1,
                  "bd_dst": 771
                },
                {
                  "dI": 3,
                  "x": 0.0,
                  "y": 0.0,
                  "z": 0,
                  "cX": 1.0,
                  "cY": 1.0,
                  "kX": 0.0,
                  "kY": 0.0,
                  "fi": 28,
                  "twE": 0,
                  "tweenFrame": true,
                  "bd_src": 1,
                  "bd_dst": 771
                }
              ]
            }
          ]
        },
        {
          "name": "Spell",
          "dr": 80,
          "lp": true,
          "to": 0,
          "drTW": 0,
          "twE": 0,
          "sc": 1.0,
          "mov_bone_data": [
            {
              "name": "FireBall",
              "dl": 0.0,
              "frame_data": [
                {
                  "dI": 1,
                  "x": 0.0,
                  "y": 0.0,
                  "z": 0,
                  "cX": 1.0,
                  "cY": 1.0,
                  "kX": 0.0,
                  "kY": 0.0,
                  "fi": 0,
                  "twE": 0,
                  "tweenFrame": true,
                  "bd_src": 1,
                  "bd_dst": 771
                },
                {
                  "dI": 0,
                  "x": 0.0,
                  "y": 0.0,
                  "z": 0,
                  "cX": 1.0,
                  "cY": 1.0,
                  "kX": 0.0,
                  "kY": 0.0,
                  "fi": 25,
                  "twE": 0,
                  "tweenFrame": true,
                  "bd_src": 1,
                  "bd_dst": 771
                },
                {
                  "dI": 2,
                  "x": 0.0,
                  "y": 0.0,
                  "z": 0,
                  "cX": 1.0,
                  "cY": 1.0,
                  "kX": 0.0,
                  "kY": 0.0,
                  "fi": 30,
                  "twE": 0,
                  "tweenFrame": true,
                  "bd_src": 1,
                  "bd_dst": 771
                },
                {
                  "dI": 3,
                  "x": 0.0,
                  "y": 0.0,
                  "z": 0,
                  "cX": 1.0,
                  "cY": 1.0,
                  "kX": 0.0,
                  "kY": 0.0,
                  "fi": 35,
                  "twE": 0,
                  "tweenFrame": true,
                  "bd_src": 1,
                  "bd_dst": 771
                },
                {
                  "dI": 4,
                  "x": 0.0,
                  "y": 0.0,
                  "z": 0,
                  "cX": 1.0,
                  "cY": 1.0,
                  "kX": 0.0,
                  "kY": 0.0,
                  "fi": 40,
                  "twE": 0,
                  "tweenFrame": true,
                  "bd_src": 1,
                  "bd_dst": 771
                },
                {
                  "dI": 0,
                  "x": 0.0,
                  "y": 0.0,
                  "z": 0,
                  "cX": 1.0,
                  "cY": 1.0,
                  "kX": 0.0,
                  "kY": 0.0,
                  "fi": 45,
                  "twE": 0,
                  "tweenFrame": true,
                  "bd_src": 1,
                  "bd_dst": 771
                },
                {
                  "dI": 2,
                  "x": 0.0,
                  "y": 0.0,
                  "z": 0,
                  "cX": 1.0,
                  "cY": 1.0,
                  "kX": 0.0,
                  "kY": 0.0,
                  "fi": 50,
                  "twE": 0,
                  "tweenFrame": true,
                  "bd_src": 1,
                  "bd_dst": 771
                },
                {
                  "dI": 3,
                  "x": 0.0,
                  "y": 0.0,
                  "z": 0,
                  "cX": 1.0,
                  "cY": 1.0,
                  "kX": 0.0,
                  "kY": 0.0,
                  "fi": 55,
                  "twE": 0,
                  "tweenFrame": true,
                  "bd_src": 1,
                  "bd_dst": 771
                },
                {
                  "dI": 4,
                  "x": 0.0,
                  "y": 0.0,
                  "z": 0,
                  "cX": 1.0,
                  "cY": 1.0,
                  "kX": 0.0,
                  "kY": 0.0,
                  "fi": 60,
                  "twE": 0,
                  "tweenFrame": true,
                  "bd_src": 1,
                  "bd_dst": 771
                },
                {
                  "dI": 0,
                  "x": 0.0,
                  "y": 0.0,
                  "z": 0,
                  "cX": 1.0,
                  "cY": 1.0,
                  "kX": 0.0,
                  "kY": 0.0,
                  "fi": 65,
                  "twE": 0,
                  "tweenFrame": true,
                  "bd_src": 1,
                  "bd_dst": 771
                },
                {
                  "dI": 2,
                  "x": 0.0,
                  "y": 0.0,
                  "z": 0,
                  "cX": 1.0,
                  "cY": 1.0,
                  "kX": 0.0,
                  "kY": 0.0,
                  "fi": 70,
                  "twE": 0,
                  "tweenFrame": true,
                  "bd_src": 1,
                  "bd_dst": 771
                },
                {
                  "dI": 0,
                  "x": 0.0,
                  "y": 0.0,
                  "z": 0,
                  "cX": 1.0,
                  "cY": 1.0,
                  "kX": 0.0,
                  "kY": 0.0,
                  "fi": 75,
                  "twE": 0,
                  "tweenFrame": true,
                  "bd_src": 1,
                  "bd_dst": 771
                },
                {
                  "dI": 2,
                  "x": 0.0,
                  "y": 0.0,
                  "z": 0,
                  "cX": 1.0,
                  "cY": 1.0,
                  "kX": 0.0,
                  "kY": 0.0,
                  "fi": 80,
                  "twE": 0,
                  "tweenFrame": true,
                  "bd_src": 1,
                  "bd_dst": 771
                }
              ]
            },
            {
              "name": "Fire_Copy5",
              "dl": 0.0,
              "frame_data": [
                {
                  "dI": 1,
                  "x": -14.189743041992188,
                  "y": -5.5333251953125,
                  "z": 0,
                  "cX": 1.0,
                  "cY": 1.0,
                  "kX": 0.0,
                  "kY": 0.0,
                  "fi": 0,
                  "twE": 0,
                  "tweenFrame": true,
                  "bd_src": 1,
                  "bd_dst": 771
                },
                {
                  "dI": 0,
                  "x": -14.189743041992188,
                  "y": -5.5333251953125,
                  "z": 0,
                  "cX": 1.0,
                  "cY": 1.0,
                  "kX": 0.0,
                  "kY": 0.0,
                  "fi": 20,
                  "twE": 0,
                  "tweenFrame": true,
                  "bd_src": 1,
                  "bd_dst": 771
                }
              ]
            },
            {
              "name": "Fire_Copy6",
              "dl": 0.0,
              "frame_data": [
                {
                  "dI": 1,
                  "x": 0.61025619506835938,
                  "y": -2.1333274841308594,
                  "z": 0,
                  "cX": 1.0,
                  "cY": 1.0,
                  "kX": 0.0,
                  "kY": 0.0,
                  "fi": 0,
                  "twE": 0,
                  "tweenFrame": true,
                  "bd_src": 1,
                  "bd_dst": 771
                },
                {
                  "dI": 0,
                  "x": 0.61025619506835938,
                  "y": -2.1333274841308594,
                  "z": 0,
                  "cX": 1.0,
                  "cY": 1.0,
                  "kX": 0.0,
                  "kY": 0.0,
                  "fi": 20,
                  "twE": 0,
                  "tweenFrame": true,
                  "bd_src": 1,
                  "bd_dst": 771
                }
              ]
            },
            {
              "name": "Fire_Copy7",
              "dl": 0.0,
              "frame_data": [
                {
                  "dI": 1,
                  "x": -6.3897433280944824,
                  "y": -10.333332061767578,
                  "z": 0,
                  "cX": 1.0,
                  "cY": 1.0,
                  "kX": 0.0,
                  "kY": 0.0,
                  "fi": 0,
                  "twE": 0,
                  "tweenFrame": true,
                  "bd_src": 1,
                  "bd_dst": 771
                },
                {
                  "dI": 0,
                  "x": -6.3897433280944824,
                  "y": -10.333332061767578,
                  "z": 0,
                  "cX": 1.0,
                  "cY": 1.0,
                  "kX": 0.0,
                  "kY": 0.0,
                  "fi": 20,
                  "twE": 0,
                  "tweenFrame": true,
                  "bd_src": 1,
                  "bd_dst": 771
                }
              ]
            },
            {
              "name": "Fire",
              "dl": 0.0,
              "frame_data": [
                {
                  "dI": 1,
                  "x": -6.1897439956665039,
                  "y": 4.0666618347167969,
                  "z": 0,
                  "cX": 1.0,
                  "cY": 1.0,
                  "kX": 0.0,
                  "kY": 0.0,
                  "fi": 0,
                  "twE": 0,
                  "tweenFrame": true,
                  "bd_src": 1,
                  "bd_dst": 771
                },
                {
                  "dI": 0,
                  "x": -6.1897439956665039,
                  "y": 4.0666618347167969,
                  "z": 0,
                  "cX": 1.0,
                  "cY": 1.0,
                  "kX": 0.0,
                  "kY": 0.0,
                  "fi": 20,
                  "twE": 0,
                  "tweenFrame": true,
                  "bd_src": 1,
                  "bd_dst": 771
                }
              ]
            },
            {
              "name": "Body",
              "dl": 0.0,
              "frame_data": [
                {
                  "dI": 4,
                  "x": 0.0,
                  "y": 0.0,
                  "z": 0,
                  "cX": 1.0,
                  "cY": 1.0,
                  "kX": 0.0,
                  "kY": 0.0,
                  "fi": 0,
                  "twE": 0,
                  "tweenFrame": true,
                  "bd_src": 1,
                  "bd_dst": 771
                },
                {
                  "dI": 5,
                  "x": 0.0,
                  "y": 0.0,
                  "z": 0,
                  "cX": 1.0,
                  "cY": 1.0,
                  "kX": 0.0,
                  "kY": 0.0,
                  "fi": 4,
                  "twE": 0,
                  "tweenFrame": true,
                  "bd_src": 1,
                  "bd_dst": 771
                },
                {
                  "dI": 6,
                  "x": 0.0,
                  "y": 0.0,
                  "z": 0,
                  "cX": 1.0,
                  "cY": 1.0,
                  "kX": 0.0,
                  "kY": 0.0,
                  "fi": 8,
                  "twE": 0,
                  "tweenFrame": true,
                  "bd_src": 1,
                  "bd_dst": 771
                },
                {
                  "dI": 7,
                  "x": 0.0,
                  "y": 0.0,
                  "z": 0,
                  "cX": 1.0,
                  "cY": 1.0,
                  "kX": 0.0,
                  "kY": 0.0,
                  "fi": 12,
                  "twE": 0,
                  "tweenFrame": true,
                  "bd_src": 1,
                  "bd_dst": 771
                },
                {
                  "dI": 8,
                  "x": 0.0,
                  "y": 0.0,
                  "z": 0,
                  "cX": 1.0,
                  "cY": 1.0,
                  "kX": 0.0,
                  "kY": 0.0,
                  "fi": 16,
                  "twE": 0,
                  "tweenFrame": true,
                  "bd_src": 1,
                  "bd_dst": 771
                },
                {
                  "dI": 9,
                  "x": 0.0,
                  "y": 0.0,
                  "z": 0,
                  "cX": 1.0,
                  "cY": 1.0,
                  "kX": 0.0,
                  "kY": 0.0,
                  "fi": 20,
                  "twE": 0,
                  "tweenFrame": true,
                  "bd_src": 1,
                  "bd_dst": 771
                },
                {
                  "dI": 10,
                  "x": 0.0,
                  "y": 0.0,
                  "z": 0,
                  "cX": 1.0,
                  "cY": 1.0,
                  "kX": 0.0,
                  "kY": 0.0,
                  "fi": 40,
                  "twE": 0,
                  "tweenFrame": true,
                  "bd_src": 1,
                  "bd_dst": 771
                },
                {
                  "dI": 11,
                  "x": 0.0,
                  "y": 0.0,
                  "z": 0,
                  "cX": 1.0,
                  "cY": 1.0,
                  "kX": 0.0,
                  "kY": 0.0,
                  "fi": 45,
                  "twE": 0,
                  "tweenFrame": true,
                  "bd_src": 1,
                  "bd_dst": 771
                },
                {
                  "dI": 12,
                  "x": 0.0,
                  "y": 0.0,
                  "z": 0,
                  "cX": 1.0,
                  "cY": 1.0,
                  "kX": 0.0,
                  "kY": 0.0,
                  "fi": 50,
                  "twE": 0,
                  "tweenFrame": true,
                  "bd_src": 1,
                  "bd_dst": 771
                },
                {
                  "dI": 13,
                  "x": 0.0,
                  "y": 0.0,
                  "z": 0,
                  "cX": 1.0,
                  "cY": 1.0,
                  "kX": 0.0,
                  "kY": 0.0,
                  "fi": 65,
                  "twE": 0,
                  "tweenFrame": true,
                  "bd_src": 1,
                  "bd_dst": 771
                },
                {
                  "dI": 14,
                  "x": 0.0,
                  "y": 0.0,
                  "z": 0,
                  "cX": 1.0,
                  "cY": 1.0,
                  "kX": 0.0,
                  "kY": 0.0,
                  "fi": 70,
                  "twE": 0,
                  "tweenFrame": true,
                  "bd_src": 1,
                  "bd_dst": 771
                },
                {
                  "dI": 15,
                  "x": 0.0,
                  "y": 0.0,
                  "z": 0,
                  "cX": 1.0,
                  "cY": 1.0,
                  "kX": 0.0,
                  "kY": 0.0,
                  "fi": 75,
                  "twE": 0,
                  "tweenFrame": true,
                  "bd_src": 1,
                  "bd_dst": 771
                },
                {
                  "dI": 16,
                  "x": 0.0,
                  "y": 0.0,
                  "z": 0,
                  "cX": 1.0,
                  "cY": 1.0,
                  "kX": 0.0,
                  "kY": 0.0,
                  "fi": 80,
                  "twE": 0,
                  "tweenFrame": true,
                  "bd_src": 1,
                  "bd_dst": 771
                }
              ]
            }
          ]
        },
        {
          "name": "FireBallExplosion",
          "dr": 35,
          "lp": true,
          "to": 0,
          "drTW": 0,
          "twE": 0,
          "sc": 1.0,
          "mov_bone_data": [
            {
              "name": "FireBall",
              "dl": 0.0,
              "frame_data": [
                {
                  "dI": 5,
                  "x": 0.0,
                  "y": 0.0,
                  "z": 0,
                  "cX": 1.0,
                  "cY": 1.0,
                  "kX": 0.0,
                  "kY": 0.0,
                  "fi": 0,
                  "twE": 0,
                  "tweenFrame": true,
                  "bd_src": 1,
                  "bd_dst": 771
                },
                {
                  "dI": 6,
                  "x": 0.0,
                  "y": 0.0,
                  "z": 0,
                  "cX": 1.0,
                  "cY": 1.0,
                  "kX": 0.0,
                  "kY": 0.0,
                  "fi": 5,
                  "twE": 0,
                  "tweenFrame": true,
                  "bd_src": 1,
                  "bd_dst": 771
                },
                {
                  "dI": 7,
                  "x": 0.0,
                  "y": 0.0,
                  "z": 0,
                  "cX": 1.0,
                  "cY": 1.0,
                  "kX": 0.0,
                  "kY": 0.0,
                  "fi": 10,
                  "twE": 0,
                  "tweenFrame": true,
                  "bd_src": 1,
                  "bd_dst": 771
                },
                {
                  "dI": 8,
                  "x": 0.0,
                  "y": 0.0,
                  "z": 0,
                  "cX": 1.0,
                  "cY": 1.0,
                  "kX": 0.0,
                  "kY": 0.0,
                  "fi": 15,
                  "twE": 0,
                  "tweenFrame": true,
                  "bd_src": 1,
                  "bd_dst": 771
                },
                {
                  "dI": 9,
                  "x": 0.0,
                  "y": 0.0,
                  "z": 0,
                  "cX": 1.0,
                  "cY": 1.0,
                  "kX": 0.0,
                  "kY": 0.0,
                  "fi": 20,
                  "twE": 0,
                  "tweenFrame": true,
                  "bd_src": 1,
                  "bd_dst": 771
                },
                {
                  "dI": 10,
                  "x": 0.0,
                  "y": 0.0,
                  "z": 0,
                  "cX": 1.0,
                  "cY": 1.0,
                  "kX": 0.0,
                  "kY": 0.0,
                  "fi": 25,
                  "twE": 0,
                  "tweenFrame": true,
                  "bd_src": 1,
                  "bd_dst": 771
                },
                {
                  "dI": 11,
                  "x": 0.0,
                  "y": 0.0,
                  "z": 0,
                  "cX": 1.0,
                  "cY": 1.0,
                  "kX": 0.0,
                  "kY": 0.0,
                  "fi": 30,
                  "twE": 0,
                  "tweenFrame": true,
                  "bd_src": 1,
                  "bd_dst": 771
                },
                {
                  "dI": 1,
                  "x": 0.0,
                  "y": 0.0,
                  "z": 0,
                  "cX": 1.0,
                  "cY": 1.0,
                  "kX": 0.0,
                  "kY": 0.0,
                  "fi": 35,
                  "twE": 0,
                  "tweenFrame": true,
                  "bd_src": 1,
                  "bd_dst": 771
                }
              ]
            }
          ]
        },
        {
          "name": "FireBall",
          "dr": 20,
          "lp": true,
          "to": 0,
          "drTW": 0,
          "twE": 0,
          "sc": 1.0,
          "mov_bone_data": [
            {
              "name": "FireBall",
              "dl": 0.0,
              "frame_data": [
                {
                  "dI": 0,
                  "x": 0.0,
                  "y": 0.0,
                  "z": 0,
                  "cX": 0.4999999,
                  "cY": 0.4999999,
                  "kX": 0.0,
                  "kY": 0.0,
                  "fi": 0,
                  "twE": 0,
                  "tweenFrame": true,
                  "bd_src": 1,
                  "bd_dst": 771
                },
                {
                  "dI": 2,
                  "x": 0.0,
                  "y": 0.0,
                  "z": 0,
                  "cX": 0.4999999,
                  "cY": 0.4999999,
                  "kX": 0.0,
                  "kY": 0.0,
                  "fi": 5,
                  "twE": 0,
                  "tweenFrame": true,
                  "bd_src": 1,
                  "bd_dst": 771
                },
                {
                  "dI": 3,
                  "x": 0.0,
                  "y": 0.0,
                  "z": 0,
                  "cX": 0.4999999,
                  "cY": 0.4999999,
                  "kX": 0.0,
                  "kY": 0.0,
                  "fi": 10,
                  "twE": 0,
                  "tweenFrame": true,
                  "bd_src": 1,
                  "bd_dst": 771
                },
                {
                  "dI": 4,
                  "x": 0.0,
                  "y": 0.0,
                  "z": 0,
                  "cX": 0.4999999,
                  "cY": 0.4999999,
                  "kX": 0.0,
                  "kY": 0.0,
                  "fi": 15,
                  "twE": 0,
                  "tweenFrame": true,
                  "bd_src": 1,
                  "bd_dst": 771
                },
                {
                  "dI": 4,
                  "x": 0.0,
                  "y": 0.0,
                  "z": 0,
                  "cX": 0.4999999,
                  "cY": 0.4999999,
                  "kX": 0.0,
                  "kY": 0.0,
                  "fi": 20,
                  "twE": 0,
                  "tweenFrame": true,
                  "bd_src": 1,
                  "bd_dst": 771
                }
              ]
            }
          ]
        },
        {
          "name": "Die",
          "dr": 31,
          "lp": true,
          "to": 0,
          "drTW": 0,
          "twE": 0,
          "sc": 1.0,
          "mov_bone_data": [
            {
              "name": "FireBall",
              "dl": 0.0,
              "frame_data": [
                {
                  "dI": 12,
                  "x": 0.0,
                  "y": 0.0,
                  "z": 0,
                  "cX": 1.0,
                  "cY": 1.0,
                  "kX": 0.0,
                  "kY": 0.0,
                  "fi": 0,
                  "twE": 0,
                  "tweenFrame": true,
                  "bd_src": 1,
                  "bd_dst": 771
                },
                {
                  "dI": 12,
                  "x": 0.0,
                  "y": 0.0,
                  "z": 0,
                  "cX": 1.0,
                  "cY": 1.0,
                  "kX": 0.0,
                  "kY": 0.0,
                  "fi": 30,
                  "twE": 0,
                  "tweenFrame": true,
                  "bd_src": 1,
                  "bd_dst": 771
                }
              ]
            }
          ]
        }
      ]
    }
  ],
  "texture_data": [
    {
      "name": "EnemyWizardIdle_Sprite_0",
      "width": 33.0,
      "height": 45.0,
      "pX": 0.5,
      "pY": 0.5,
      "plistFile": "enemyFinal1Spritesheet.plist"
    },
    {
      "name": "EnemyWizardIdle_Sprite_1",
      "width": 34.0,
      "height": 45.0,
      "pX": 0.5,
      "pY": 0.5,
      "plistFile": "enemyFinal1Spritesheet.plist"
    },
    {
      "name": "EnemyWizardIdle_Sprite_2",
      "width": 34.0,
      "height": 44.0,
      "pX": 0.5,
      "pY": 0.5,
      "plistFile": "enemyFinal1Spritesheet.plist"
    },
    {
      "name": "EnemyWizardIdle_Sprite_3",
      "width": 34.0,
      "height": 44.0,
      "pX": 0.5,
      "pY": 0.5,
      "plistFile": "enemyFinal1Spritesheet.plist"
    },
    {
      "name": "EnemyWizardSpell_Sprite_0",
      "width": 0.0,
      "height": 0.0,
      "pX": 0.5,
      "pY": 0.5,
      "plistFile": "enemyFinal1Spritesheet.plist"
    },
    {
      "name": "EnemyWizardSpell_Sprite_1",
      "width": 43.0,
      "height": 45.0,
      "pX": 0.5,
      "pY": 0.5,
      "plistFile": "enemyFinal1Spritesheet.plist"
    },
    {
      "name": "EnemyWizardSpell_Sprite_2",
      "width": 44.0,
      "height": 44.0,
      "pX": 0.5,
      "pY": 0.5,
      "plistFile": "enemyFinal1Spritesheet.plist"
    },
    {
      "name": "EnemyWizardSpell_Sprite_3",
      "width": 38.0,
      "height": 44.0,
      "pX": 0.5,
      "pY": 0.5,
      "plistFile": "enemyFinal1Spritesheet.plist"
    },
    {
      "name": "EnemyWizardSpell_Sprite_4",
      "width": 35.0,
      "height": 45.0,
      "pX": 0.5,
      "pY": 0.5,
      "plistFile": "enemyFinal1Spritesheet.plist"
    },
    {
      "name": "EnemyWizardSpell_Sprite_5",
      "width": 32.0,
      "height": 45.0,
      "pX": 0.5,
      "pY": 0.5,
      "plistFile": "enemyFinal1Spritesheet.plist"
    },
    {
      "name": "EnemyWizardSpell_Sprite_6",
      "width": 44.0,
      "height": 43.0,
      "pX": 0.5,
      "pY": 0.5,
      "plistFile": "enemyFinal1Spritesheet.plist"
    },
    {
      "name": "EnemyWizardSpell_Sprite_7",
      "width": 47.0,
      "height": 41.0,
      "pX": 0.5,
      "pY": 0.5,
      "plistFile": "enemyFinal1Spritesheet.plist"
    },
    {
      "name": "EnemyWizardSpell_Sprite_8",
      "width": 48.0,
      "height": 41.0,
      "pX": 0.5,
      "pY": 0.5,
      "plistFile": "enemyFinal1Spritesheet.plist"
    },
    {
      "name": "EnemyWizardSpell_Sprite_9",
      "width": 47.0,
      "height": 42.0,
      "pX": 0.5,
      "pY": 0.5,
      "plistFile": "enemyFinal1Spritesheet.plist"
    },
    {
      "name": "EnemyWizardSpell_Sprite_10",
      "width": 42.0,
      "height": 42.0,
      "pX": 0.5,
      "pY": 0.5,
      "plistFile": "enemyFinal1Spritesheet.plist"
    },
    {
      "name": "EnemyWizardSpell_Sprite_11",
      "width": 37.0,
      "height": 42.0,
      "pX": 0.5,
      "pY": 0.5,
      "plistFile": "enemyFinal1Spritesheet.plist"
    },
    {
      "name": "EnemyWizardSpell_Sprite_12",
      "width": 33.0,
      "height": 44.0,
      "pX": 0.5,
      "pY": 0.5,
      "plistFile": "enemyFinal1Spritesheet.plist"
    },
    {
      "name": "WizardFireParticle_Sprite_0",
      "width": 3.0,
      "height": 6.0,
      "pX": 0.5,
      "pY": 0.5,
      "plistFile": "enemyFinal1Spritesheet.plist"
    },
    {
      "name": "WizardFireballProjectile_Sprite_0",
      "width": 44.0,
      "height": 42.0,
      "pX": 0.5,
      "pY": 0.5,
      "plistFile": "enemyFinal1Spritesheet.plist"
    },
    {
      "name": "WizardFireballProjectileExplosion_Sprite_7",
      "width": 1.0,
      "height": 1.0,
      "pX": 0.5,
      "pY": 0.5,
      "plistFile": "enemyFinal1Spritesheet.plist"
    },
    {
      "name": "WizardFireballProjectile_Sprite_1",
      "width": 44.0,
      "height": 46.0,
      "pX": 0.5,
      "pY": 0.5,
      "plistFile": "enemyFinal1Spritesheet.plist"
    },
    {
      "name": "WizardFireballProjectile_Sprite_2",
      "width": 44.0,
      "height": 54.0,
      "pX": 0.5,
      "pY": 0.5,
      "plistFile": "enemyFinal1Spritesheet.plist"
    },
    {
      "name": "WizardFireballProjectile_Sprite_3",
      "width": 44.0,
      "height": 52.0,
      "pX": 0.5,
      "pY": 0.5,
      "plistFile": "enemyFinal1Spritesheet.plist"
    },
    {
      "name": "WizardFireballProjectileExplosion_Sprite_0",
      "width": 38.0,
      "height": 40.0,
      "pX": 0.5,
      "pY": 0.5,
      "plistFile": "enemyFinal1Spritesheet.plist"
    },
    {
      "name": "WizardFireballProjectileExplosion_Sprite_1",
      "width": 0.0,
      "height": 0.0,
      "pX": 0.5,
      "pY": 0.5,
      "plistFile": "enemyFinal1Spritesheet.plist"
    },
    {
      "name": "WizardFireballProjectileExplosion_Sprite_2",
      "width": 0.0,
      "height": 0.0,
      "pX": 0.5,
      "pY": 0.5,
      "plistFile": "enemyFinal1Spritesheet.plist"
    },
    {
      "name": "WizardFireballProjectileExplosion_Sprite_3",
      "width": 0.0,
      "height": 0.0,
      "pX": 0.5,
      "pY": 0.5,
      "plistFile": "enemyFinal1Spritesheet.plist"
    },
    {
      "name": "WizardFireballProjectileExplosion_Sprite_4",
      "width": 0.0,
      "height": 0.0,
      "pX": 0.5,
      "pY": 0.5,
      "plistFile": "enemyFinal1Spritesheet.plist"
    },
    {
      "name": "WizardFireballProjectileExplosion_Sprite_5",
      "width": 0.0,
      "height": 0.0,
      "pX": 0.5,
      "pY": 0.5,
      "plistFile": "enemyFinal1Spritesheet.plist"
    },
    {
      "name": "WizardFireballProjectileExplosion_Sprite_6",
      "width": 0.0,
      "height": 0.0,
      "pX": 0.5,
      "pY": 0.5,
      "plistFile": "enemyFinal1Spritesheet.plist"
    },
    {
      "name": "ExplosionBrown_Sprite_0",
      "width": 68.0,
      "height": 66.0,
      "pX": 0.5,
      "pY": 0.5,
      "plistFile": ""
    }
  ],
  "config_file_path": [
    "enemyFinal1Spritesheet.plist",
    "FinalAnimation_enemy10.plist"
  ],
  "config_png_path": [
    "enemyFinal1Spritesheet.png",
    "FinalAnimation_enemy10.png"
  ]
}