<xml>
  <instance name="MPBar_Sprite" index="0" posX="0" posY="0" anchorX="0" anchorY="0" width="32" height="12"/>
  <instance name="PlayerHUDLvlText_Sprite" index="0" posX="33" posY="0" anchorX="0" anchorY="0" width="27" height="19"/>
  <instance name="PlayerUICoin_Sprite" index="0" posX="61" posY="0" anchorX="0" anchorY="0" width="22" height="26"/>
  <instance name="HPBar_Sprite" index="0" posX="84" posY="0" anchorX="0" anchorY="0" width="32" height="20"/>
  <instance name="MPBarLeft_Sprite" index="0" posX="117" posY="0" anchorX="0" anchorY="0" width="32" height="24"/>
  <instance name="MPBarMid_Sprite" index="0" posX="150" posY="0" anchorX="0" anchorY="0" width="32" height="24"/>
  <instance name="MPBarRight_Sprite" index="0" posX="183" posY="0" anchorX="0" anchorY="0" width="32" height="24"/>
  <instance name="HPBarLeft_Sprite" index="0" posX="216" posY="0" anchorX="0" anchorY="0" width="32" height="34"/>
  <instance name="HPBarMid_Sprite" index="0" posX="249" posY="0" anchorX="0" anchorY="0" width="32" height="34"/>
  <instance name="HPBarRight_Sprite" index="0" posX="282" posY="0" anchorX="0" anchorY="0" width="32" height="34"/>
  <instance name="GamepadStartButton_Sprite" index="0" posX="315" posY="0" anchorX="25" anchorY="14.35" width="50" height="28"/>
  <instance name="GamepadBackButton_Sprite" index="0" posX="366" posY="0" anchorX="25" anchorY="14.35" width="50" height="28"/>
  <instance name="EnemyHPBar_Sprite" index="0" posX="0" posY="27" anchorX="0" anchorY="0" width="200" height="10"/>
  <instance name="GamepadRightStick_Sprite" index="0" posX="201" posY="35" anchorX="32" anchorY="31" width="64" height="62"/>
  <instance name="GamepadLeftStick_Sprite" index="0" posX="266" posY="35" anchorX="32" anchorY="31" width="64" height="62"/>
  <instance name="GamepadRightButton_Sprite" index="0" posX="331" posY="29" anchorX="50" anchorY="20.5" width="100" height="40"/>
  <instance name="GamepadLeftButton_Sprite" index="0" posX="0" posY="38" anchorX="50" anchorY="20" width="100" height="40"/>
  <instance name="GamepadYButton_Sprite" index="0" posX="101" posY="38" anchorX="32" anchorY="32" width="64" height="64"/>
  <instance name="GamepadXButton_Sprite" index="0" posX="166" posY="98" anchorX="32" anchorY="32" width="64" height="64"/>
  <instance name="GamepadUpArrow_Sprite" index="0" posX="231" posY="98" anchorX="32" anchorY="32" width="64" height="64"/>
  <instance name="GamepadRightArrow_Sprite" index="0" posX="296" posY="98" anchorX="32" anchorY="32" width="64" height="64"/>
  <instance name="GamepadLeftArrow_Sprite" index="0" posX="361" posY="70" anchorX="32" anchorY="32" width="64" height="64"/>
  <instance name="GamepadDownArrow_Sprite" index="0" posX="426" posY="70" anchorX="32" anchorY="32" width="64" height="64"/>
  <instance name="GamepadBButton_Sprite" index="0" posX="0" posY="79" anchorX="32" anchorY="32" width="64" height="64"/>
  <instance name="GamepadAButton_Sprite" index="0" posX="65" posY="103" anchorX="32" anchorY="32" width="64" height="64"/>
  <instance name="GamepadLeftTrigger_Sprite" index="0" posX="130" posY="163" anchorX="33" anchorY="54.2" width="66" height="107"/>
  <instance name="GamepadRightTrigger_Sprite" index="0" posX="197" posY="163" anchorX="33" anchorY="54.2" width="66" height="108"/>
  <instance name="EnemyHUD_Sprite" index="0" posX="264" posY="163" anchorX="0" anchorY="0" width="216" height="35"/>
  <instance name="KeyboardButton_Sprite" index="0" posX="0" posY="168" anchorX="47" anchorY="44" width="94" height="88"/>
  <instance name="KeyboardArrowDown_Sprite" index="0" posX="95" posY="271" anchorX="47" anchorY="44" width="94" height="88"/>
  <instance name="KeyboardArrowLeft_Sprite" index="0" posX="190" posY="272" anchorX="47" anchorY="44" width="94" height="88"/>
  <instance name="KeyboardArrowRight_Sprite" index="0" posX="285" posY="199" anchorX="47" anchorY="44" width="94" height="88"/>
  <instance name="KeyboardArrowUp_Sprite" index="0" posX="380" posY="199" anchorX="47" anchorY="44" width="94" height="88"/>
  <instance name="KeyboardButtonLong_Sprite" index="0" posX="0" posY="360" anchorX="77" anchorY="44" width="154" height="88"/>
  <instance name="KeyboardSpacebar_Sprite" index="0" posX="155" posY="361" anchorX="142" anchorY="44" width="284" height="88"/>
  <animation frame="1" name="EnemyHPBar_Sprite" index="0" duration="1" label=""/>
  <animation frame="1" name="EnemyHUD_Sprite" index="0" duration="1" label=""/>
  <animation frame="1" name="PlayerHUDLvlText_Sprite" index="0" duration="1" label=""/>
  <animation frame="1" name="PlayerUICoin_Sprite" index="0" duration="1" label=""/>
  <animation frame="1" name="GamepadYButton_Sprite" index="0" duration="1" label=""/>
  <animation frame="1" name="GamepadXButton_Sprite" index="0" duration="1" label=""/>
  <animation frame="1" name="GamepadStartButton_Sprite" index="0" duration="1" label=""/>
  <animation frame="1" name="GamepadRightTrigger_Sprite" index="0" duration="1" label=""/>
  <animation frame="1" name="GamepadRightStick_Sprite" index="0" duration="1" label=""/>
  <animation frame="1" name="GamepadRightButton_Sprite" index="0" duration="1" label=""/>
  <animation frame="1" name="GamepadLeftTrigger_Sprite" index="0" duration="1" label=""/>
  <animation frame="1" name="GamepadLeftStick_Sprite" index="0" duration="1" label=""/>
  <animation frame="1" name="GamepadLeftButton_Sprite" index="0" duration="1" label=""/>
  <animation frame="1" name="GamepadUpArrow_Sprite" index="0" duration="1" label=""/>
  <animation frame="1" name="GamepadRightArrow_Sprite" index="0" duration="1" label=""/>
  <animation frame="1" name="GamepadLeftArrow_Sprite" index="0" duration="1" label=""/>
  <animation frame="1" name="GamepadDownArrow_Sprite" index="0" duration="1" label=""/>
  <animation frame="1" name="GamepadBButton_Sprite" index="0" duration="1" label=""/>
  <animation frame="1" name="GamepadAButton_Sprite" index="0" duration="1" label=""/>
  <animation frame="1" name="GamepadBackButton_Sprite" index="0" duration="1" label=""/>
  <animation frame="1" name="KeyboardButton_Sprite" index="0" duration="1" label=""/>
  <animation frame="1" name="KeyboardButtonLong_Sprite" index="0" duration="1" label=""/>
  <animation frame="1" name="KeyboardSpacebar_Sprite" index="0" duration="1" label=""/>
  <animation frame="1" name="KeyboardArrowDown_Sprite" index="0" duration="1" label=""/>
  <animation frame="1" name="KeyboardArrowLeft_Sprite" index="0" duration="1" label=""/>
  <animation frame="1" name="KeyboardArrowRight_Sprite" index="0" duration="1" label=""/>
  <animation frame="1" name="KeyboardArrowUp_Sprite" index="0" duration="1" label=""/>
  <animation frame="1" name="HPBar_Sprite" index="0" duration="1" label=""/>
  <animation frame="1" name="MPBar_Sprite" index="0" duration="1" label=""/>
  <animation frame="1" name="MPBarLeft_Sprite" index="0" duration="1" label=""/>
  <animation frame="1" name="MPBarMid_Sprite" index="0" duration="1" label=""/>
  <animation frame="1" name="MPBarRight_Sprite" index="0" duration="1" label=""/>
  <animation frame="1" name="HPBarLeft_Sprite" index="0" duration="1" label=""/>
  <animation frame="1" name="HPBarMid_Sprite" index="0" duration="1" label=""/>
  <animation frame="1" name="HPBarRight_Sprite" index="0" duration="1" label=""/>
  <container name="PlayerHUDMPBar_Character" child="MPBarLeft_Sprite" childX="0" childY="0" childRotation="0"/>
  <container name="PlayerHUDMPBar_Character" child="MPBarMid_Sprite" childX="32" childY="0" childRotation="0"/>
  <container name="PlayerHUDMPBar_Character" child="MPBarRight_Sprite" childX="64" childY="0" childRotation="0"/>
  <container name="PlayerHUDHPBar_Character" child="HPBarLeft_Sprite" childX="0" childY="0" childRotation="0"/>
  <container name="PlayerHUDHPBar_Character" child="HPBarMid_Sprite" childX="32" childY="0" childRotation="0"/>
  <container name="PlayerHUDHPBar_Character" child="HPBarRight_Sprite" childX="64" childY="0" childRotation="0"/>
</xml>